Metadata-Version: 2.1
Name: pyUnit-math
Version: 2020.3.23
Summary: 数据分析和数学常用的方法
Home-page: https://github.com/PyUnit/pyunit-math
Author: Jtyoui
Author-email: jtyoui@qq.com
License: MIT Licence
Platform: any
Classifier: Programming Language :: Python :: 3
Classifier: Programming Language :: C
Classifier: License :: OSI Approved :: MIT License
Classifier: Operating System :: Microsoft :: Windows
Classifier: Operating System :: POSIX :: Linux
